{"392676":{"city":"\u041c\u043e\u0441\u043a\u0432\u0430","date_start":"28.08.2020","time_start":"16:00","date_end":"28.08.2020","time_end":"16:00","description":"","note":"","additional_excursions":[],"description_en":""},"392677":{"city":"\u041c\u044b\u0448\u043a\u0438\u043d","date_start":"29.08.2020","time_start":"16:30","date_end":"29.08.2020","time_end":"19:30","description":"","note":"","additional_excursions":[],"description_en":""},"392678":{"city":"\u041c\u043e\u0441\u043a\u0432\u0430","date_start":"30.08.2020","time_start":"20:00","date_end":"30.08.2020","time_end":"20:00","description":"","note":"","additional_excursions":[],"description_en":""}}